Metadata-Version: 2.1
Name: Flask-Autoversion
Version: 0.1.0
Summary: Add query parameters to static file paths.
Home-page: http://github.com/bmcculley/flask-autoversion
Author: bmcculley
Author-email: fva@pypi.e42.xyz
License: BSD
Download-URL: https://github.com/bmcculley/flask-autoversion/archive/0.1.0.tar.gz
Keywords: Web Development Tools,Flask
Platform: any
Classifier: Development Status :: 4 - Beta
Classifier: Environment :: Web Environment
Classifier: Intended Audience :: Developers
Classifier: License :: OSI Approved :: BSD License
Classifier: Operating System :: OS Independent
Classifier: Programming Language :: Python
Classifier: Topic :: Internet :: WWW/HTTP :: Dynamic Content
Classifier: Topic :: Software Development :: Libraries :: Python Modules
